pycensuskr/__init__.py
pycensuskr/pycensuskr.py
pycensuskr/data/boundaries.gpkg
pycensuskr/data/censuskor.parquet
pycensuskr-0.2.7.dist-info/licenses/LICENSE
pycensuskr-0.2.7.dist-info/METADATA
pycensuskr-0.2.7.dist-info/WHEEL
pycensuskr-0.2.7.dist-info/top_level.txt
pycensuskr-0.2.7.dist-info/RECORD
