Metadata-Version: 2.4
Name: pycensuskr
Version: 0.2.7
Summary: A Python package for Korean census data processing
Home-page: https://github.com/sigmafelix/pycensuskr
Author: Insang Song
Author-email: Insang Song <geoissong@gmail.com>, Sohyun Park <wherewindstay@gmail.com>, Hyesop Shin <hyesop.shin@auckland.ac.nz>
Maintainer-email: Insang Song <geoissong@gmail.com>
License: MIT
Project-URL: Homepage, https://github.com/sigmafelix/pycensuskr
Project-URL: Repository, https://github.com/sigmafelix/pycensuskr
Project-URL: Bug Tracker, https://github.com/sigmafelix/pycensuskr/issues
Classifier: Development Status :: 3 - Alpha
Classifier: Intended Audience :: Developers
Classifier: License :: OSI Approved :: MIT License
Classifier: Programming Language :: Python :: 3
Classifier: Programming Language :: Python :: 3.8
Classifier: Programming Language :: Python :: 3.9
Classifier: Programming Language :: Python :: 3.10
Classifier: Programming Language :: Python :: 3.11
Classifier: Programming Language :: Python :: 3.12
Requires-Python: >=3.8
License-File: LICENSE
Provides-Extra: dev
Requires-Dist: pytest>=7.0; extra == "dev"
Requires-Dist: pytest-cov>=4.0; extra == "dev"
Requires-Dist: black>=22.0; extra == "dev"
Requires-Dist: flake8>=6.0; extra == "dev"
Requires-Dist: mypy>=1.0; extra == "dev"
Dynamic: author
Dynamic: home-page
Dynamic: license-file
Dynamic: requires-python
